movieinfomaker
