Metadata-Version: 1.0
Name: movieinfomaker
Version: 0.0.6
Summary: A script that looks up all movies and TV shows in a folder and gets the  genre, runtime, plot and IMDB and RottenTomatoes ratings of the movie and stores it as a csv file.
Home-page: https://github.com/anubhabsen/movie-info
Author: Anubhab Sen
Author-email: anubhabsen@gmail.com
License: BSD
Keywords: movie data info information scrap imdb rottentomatoes
Platform: UNKNOWN
